dotx/__init__.py
dotx/always-create
dotx/cli.py
dotx/database.py
dotx/dotxignore
dotx/hierarchy.py
dotx/ignore.py
dotx/install.py
dotx/installed-schema.sql
dotx/options.py
dotx/plan.py
dotx/uninstall.py
dotx/commands/__init__.py
dotx/commands/database.py
dotx/commands/install_cmd.py
dotx/commands/path_cmd.py
dotx/commands/progress.py
dotx/commands/uninstall_cmd.py
dotx-3.3.2.dist-info/licenses/LICENSE
dotx-3.3.2.dist-info/METADATA
dotx-3.3.2.dist-info/WHEEL
dotx-3.3.2.dist-info/entry_points.txt
dotx-3.3.2.dist-info/top_level.txt
dotx-3.3.2.dist-info/RECORD
