Metadata-Version: 2.4
Name: dotx
Version: 3.3.2
Summary: A command-line tool to install a link-farm to your dotfiles
Author-email: Wolf <Wolf@zv.cx>
License-Expression: MIT
Project-URL: Homepage, https://github.com/wolf/dotx
Project-URL: Repository, https://github.com/wolf/dotx
Project-URL: Issues, https://github.com/wolf/dotx/issues
Keywords: dotfiles,symlinks,configuration,link-farm
Classifier: Development Status :: 5 - Production/Stable
Classifier: Environment :: Console
Classifier: Intended Audience :: Developers
Classifier: Operating System :: OS Independent
Classifier: Programming Language :: Python :: 3
Classifier: Programming Language :: Python :: 3.13
Classifier: Topic :: System :: Systems Administration
Classifier: Topic :: Utilities
Requires-Python: >=3.13
License-File: LICENSE
Requires-Dist: click>=8.1.7
Requires-Dist: loguru>=0.7.0
Requires-Dist: pathspec>=0.12.1
Requires-Dist: rich>=13.9.4
Requires-Dist: typer>=0.15.1
Dynamic: license-file
